compute_horde-0.0.26.dist-info/METADATA
compute_horde-0.0.26.dist-info/WHEEL
compute_horde-0.0.26.dist-info/entry_points.txt
compute_horde/__init__.py
compute_horde/base/__init__.py
compute_horde/base/admin.py
compute_horde/base/docker.py
compute_horde/blockchain/__init__.py
compute_horde/blockchain/apps.py
compute_horde/blockchain/block_cache.py
compute_horde/blockchain/tasks.py
compute_horde/dynamic_config.py
compute_horde/executor_class.py
compute_horde/fv_protocol/__init__.py
compute_horde/fv_protocol/facilitator_requests.py
compute_horde/fv_protocol/validator_requests.py
compute_horde/miner_client/__init__.py
compute_horde/miner_client/base.py
compute_horde/miner_client/organic.py
compute_horde/protocol_messages.py
compute_horde/py.typed
compute_horde/receipts/__init__.py
compute_horde/receipts/admin.py
compute_horde/receipts/apps.py
compute_horde/receipts/migrations/0001_initial.py
compute_horde/receipts/migrations/0002_jobstartedreceipt_is_organic.py
compute_horde/receipts/migrations/0003_jobacceptedreceipt_and_more.py
compute_horde/receipts/migrations/0004_remove_jobstartedreceipt_max_timeout.py
compute_horde/receipts/migrations/__init__.py
compute_horde/receipts/models.py
compute_horde/receipts/schemas.py
compute_horde/receipts/store/__init__.py
compute_horde/receipts/store/base.py
compute_horde/receipts/store/local.py
compute_horde/receipts/store/noop.py
compute_horde/receipts/transfer.py
compute_horde/receipts/transfer_checkpoints.py
compute_horde/smart_contracts/__init__.py
compute_horde/smart_contracts/abi/map_abi.json
compute_horde/smart_contracts/map_contract.py
compute_horde/smart_contracts/utils.py
compute_horde/subtensor.py
compute_horde/test_base/LICENSE
compute_horde/test_base/NOTICE
compute_horde/test_base/__init__.py
compute_horde/test_base/test_validator_requests.py
compute_horde/transport/__init__.py
compute_horde/transport/base.py
compute_horde/transport/stub.py
compute_horde/transport/ws.py
compute_horde/utils.py
compute_horde/validators/__init__.py
compute_horde/validators/apps.py
compute_horde/validators/tasks.py
compute_horde-0.0.26.dist-info/RECORD
