Metadata-Version: 2.1
Name: compute-horde
Version: 0.0.26
Author: Backend Developers LTD
License: MIT License
Requires-Python: ==3.11.*
Requires-Dist: pydantic<3,>=2.3
Requires-Dist: bittensor~=9.9
Requires-Dist: websockets<15.0,>=14.0
Requires-Dist: more-itertools>=10.2.0
Requires-Dist: requests>=2.32.2
Requires-Dist: Django~=4.2.4
Requires-Dist: cryptography>=42.0.8
Requires-Dist: celery<6,>=5.3.0
Requires-Dist: aiohttp>=3.12.0
Requires-Dist: compute-horde-sdk
Requires-Dist: rich~=13.9.4
Requires-Dist: web3==7.11.0
